main.py
setup.py
Service_Affinity_Scheduling.egg-info/PKG-INFO
Service_Affinity_Scheduling.egg-info/SOURCES.txt
Service_Affinity_Scheduling.egg-info/dependency_links.txt
Service_Affinity_Scheduling.egg-info/requires.txt
Service_Affinity_Scheduling.egg-info/top_level.txt